fastnntpy/__init__.py
fastnntpy/fastnntpy.cpython-39-x86_64-linux-gnu.so
fastnntpy-0.2.4.dist-info/METADATA
fastnntpy-0.2.4.dist-info/WHEEL
fastnntpy-0.2.4.dist-info/licenses/LICENSE
fastnntpy-0.2.4.dist-info/RECORD
