Metadata-Version: 2.4
Name: fastnntpy
Version: 0.2.4
Classifier: Programming Language :: Python :: 3
Classifier: Programming Language :: Rust
Classifier: Operating System :: OS Independent
Requires-Dist: networkx>=3 ; extra == 'plot'
Requires-Dist: matplotlib>=3 ; extra == 'plot'
Requires-Dist: pandas>=1.5 ; extra == 'plot'
Provides-Extra: plot
License-File: LICENSE
Summary: Fast NeighbourNet (Rust) with Python bindings
Author-email: Rhys Newell <rhys.newell94@gmail.com>
Requires-Python: >=3.9
Project-URL: Homepage, https://github.com/rhysnewell/fast-nnt
